breadboard_curiouschip/__init__.py
breadboard_curiouschip/breadboard.py
breadboard_curiouschip-0.0.2.dist-info/METADATA
breadboard_curiouschip-0.0.2.dist-info/WHEEL
breadboard_curiouschip-0.0.2.dist-info/licenses/LICENSE
breadboard_curiouschip-0.0.2.dist-info/RECORD
