Metadata-Version: 2.1
Name: breadboard_curiouschip
Version: 0.0.2
Summary: Client library for Curious Chip Breadboard
Project-URL: Homepage, https://github.com/curiouschip/breadboard-client-py
Author: Jason Frame
License-File: LICENSE
Classifier: License :: OSI Approved :: MIT License
Classifier: Operating System :: OS Independent
Classifier: Programming Language :: Python :: 3
Requires-Python: >=3.7
Requires-Dist: pyserial>=3
Requires-Dist: sliplib~=0.6
